ai_stocks/__init__.py
ai_stocks/base_stocks.py
ai_stocks/config.py
ai_stocks/datas/__init__.py
ai_stocks/datas/base_dataloader.py
ai_stocks/datas/operate_dataloader.py
ai_stocks/datas/price_dataloader.py
ai_stocks/datas/stock_dataloader.py
ai_stocks/datas/stock_dataset.py
ai_stocks/keras/kline_predict.py
ai_stocks/kline_predictor.py
ai_stocks/moduls/__init__.py
ai_stocks/moduls/kline_module.py
ai_stocks/moduls/lstm_module.py
ai_stocks/moduls/operate_module.py
ai_stocks/moduls/price_module.py
ai_stocks/moduls/stock_module.py
ai_stocks/predictions/__init__.py
ai_stocks/predictions/base_prediction.py
ai_stocks/predictions/kline_prediction.py
ai_stocks/predictions/operate_prediction.py
ai_stocks/predictions/price_prediction.py
ai_stocks/predictions/stock_prediction.py
ai_stocks/stock_data_handler.py
ai_stocks/stock_handler.py
ai_stocks/stock_info.py
ai_stocks/stock_predictor.py
ai_stocks/utils.py
ai_stocks-0.1.10.dist-info/METADATA
ai_stocks-0.1.10.dist-info/WHEEL
ai_stocks-0.1.10.dist-info/RECORD
