Metadata-Version: 2.1
Name: ai-stocks
Version: 0.1.10
Summary: AI Stocks 是一个强大的工具，旨在利用先进的人工智能技术为股票市场分析和预测提供支持。通过整合多种数据源和机器学习算法，该工具能够帮助投资者和分析师更深入地理解市场趋势，做出更明智的投资决策。
Author: sunjuzhong
Author-email: 129019668+sunjuzhong@users.noreply.github.com
Requires-Python: >=3.10,<4.0
Classifier: Programming Language :: Python :: 3
Classifier: Programming Language :: Python :: 3.10
Classifier: Programming Language :: Python :: 3.11
Classifier: Programming Language :: Python :: 3.12
Classifier: Programming Language :: Python :: 3.13
Requires-Dist: akshare (>=1.15.32,<2.0.0)
Requires-Dist: astock-loaders (>=0.1.8,<0.2.0)
Requires-Dist: china-stock-data (>=0.1.6,<0.2.0)
Requires-Dist: keras (>=3.7.0,<4.0.0)
Requires-Dist: matplotlib (>=3.9.2,<4.0.0)
Requires-Dist: numpy (>=2.1.3,<3.0.0)
Requires-Dist: pandas (>=2.2.3,<3.0.0)
Requires-Dist: scikit-learn (>=1.5.2,<2.0.0)
Requires-Dist: scipy (>=1.14.1,<2.0.0)
Requires-Dist: toml (>=0.10.2,<0.11.0)
Requires-Dist: torch (>=2.5.1,<3.0.0)
Requires-Dist: torchvision (>=0.20.1,<0.21.0)
